s3tail/__init__.py
s3tail/background_writer.py
s3tail/cache.py
s3tail/cli.py
s3tail/old_file_cleaner.py
s3tail/s3tail.py
s3tail-0.2.1.dist-info/DESCRIPTION.rst
s3tail-0.2.1.dist-info/METADATA
s3tail-0.2.1.dist-info/RECORD
s3tail-0.2.1.dist-info/WHEEL
s3tail-0.2.1.dist-info/entry_points.txt
s3tail-0.2.1.dist-info/metadata.json
s3tail-0.2.1.dist-info/top_level.txt
